[{
"archivo": "/Imagenes/imagenesJSON/conoAzul10.jpg",
"categoria": "Accesorios",
"color": "Azul",
"descrip": "Paquete de 10 conos para entrenamiento, color azul",
"id": 0,
"marca": "BlueDot",
"nombre": "Paquete de 10 Conos Azules",
"precio": "$199",     
"talla": "N/A",
"cantidad": "50"
},
{
  "archivo": "/Imagenes/imagenesJSON/conoNaranja15.jpg",
  "categoria": "Accesorios",
  "color": "Naranja",
  "descrip": "Paquete de 15 conos para entrenamiento de color naranja",
  "id": 1,
  "marca": "BlueDot",
  "nombre": "Paquete de 15 de Conos Naranjas",
  "precio": "$249",     
  "talla": "N/A",
  "cantidad": "50"
  },
  {
    "archivo": "/Imagenes/imagenesJSON/conoRojo10.jpg",
    "categoria": "Accesorios",
    "color": "Rojo",
    "descrip": "Paquete de 10 conos de entrenamiento de color rojo",
    "id": 2,
    "marca": "BlueDot",
    "nombre": "Paquete de 10 de Conos Rojos",
    "precio": "$199",     
    "talla": "N/A",
    "cantidad": "50"
    },
    {
      "archivo": "/Imagenes/imagenesJSON/conoMulti25.jpg",
      "categoria": "Accesorios",
      "color": "Multicolor",
      "descrip": "Paquete de 25 conos para entrenamiento de distintos colores",
      "id": 3,
      "marca": "BlueDot",
      "nombre": "Paquete de 25 de Conos Multicolor",
      "precio": "$399",     
      "talla": "N/A",
      "cantidad": "50"
      },
      {
        "archivo": "/Imagenes/imagenesJSON/conoMulti50.jpg",
        "categoria": "Accesorios",
        "color": "Multicolor",
        "descrip": "Paquete de 50 conos de entrenamiento de distintos colores",
        "id": 4,
        "marca": "BlueDot",
        "nombre": "Paquete de 50 Conos Multicolor",
        "precio": "$699",     
        "talla": "N/A",
        "cantidad": "50"
        },

{
  "archivo": "/Imagenes/imagenesJSON/platoMulti10.jpg",
  "categoria": "Accesorios",
  "color": "Multicolor",
  "descrip": "Paquete de 10 plato deportivos de distintos colores",
  "id": 5,
  "marca": "BlueDot",
  "nombre": "Paquete de 10 Platos Deportivos Multicolor",
  "precio": "$2,199",     
  "talla": "N/A",
  "cantidad": "50"
  },
  {
    "archivo": "/Imagenes/imagenesJSON/platoMulti15.jpg",
    "categoria": "Accesorios",
    "color": "Multicolor",
    "descrip": "Paquete de 15 platos deportivos, multicolor",
    "id": 6,
    "marca": "BlueDot",
    "nombre": "Paquete de 15 Platos Deportivos Multicolor",
    "precio": "$299",     
    "talla": "N/A",
    "cantidad": "50"
    },
    {
      "archivo": "/Imagenes/imagenesJSON/platoMulti25.jpg",
      "categoria": "Accesorios",
      "color": "Multicolor",
      "descrip": "Paquete de 25 platos deportivos de distintos colores",
      "id": 7,
      "marca": "BlueDot",
      "nombre": "Paquete de 25 platos Deportivos",
      "precio": "$449",     
      "talla": "N/A",
      "cantidad": "50"
      },
      {
        "archivo": "/Imagenes/imagenesJSON/platoMulti50.jpg",
        "categoria": "Accesorios",
        "color": "Multicolor",
        "descrip": "Paquete de 50 platos deportivos de distintos colores",
        "id": 7,
        "marca": "BlueDot",
        "nombre": "Paquete 50 de Conos Deportivos Multicolor",
        "precio": "$799",     
        "talla": "N/A",
        "cantidad": "50"
        },
        {
          "archivo": "/Imagenes/imagenesJSON/platoNaranja10.jpg",
          "categoria": "Accesorios",
          "color": "Multicolor",
          "descrip": "Paquete de 10 platos deportivos de color naranja",
          "id": 7,
          "marca": "BlueDot",
          "nombre": "Paquete 10 de Conos Deportivos Naranja",
          "precio": "$799",     
          "talla": "N/A",
          "cantidad": "50"
          }
      
]